safe_and_collaborative_architecture-0.2.dist-info/METADATA
safe_and_collaborative_architecture-0.2.dist-info/RECORD
safe_and_collaborative_architecture-0.2.dist-info/WHEEL
safe_and_collaborative_architecture-0.2.dist-info/top_level.txt
sca/__init__.py
sca/format_flags.py
sca/formats/__init__.py
sca/formats/csv.py
sca/formats/json.py
sca/storage/__init__.py
sca/storage/repository.py
sca/utils/__init__.py
sca/utils/hash_utils.py
sca/utils/send2trash_wrapper.py
