Metadata-Version: 2.1
Name: safe-and-collaborative-architecture
Version: 0.2
Summary: This library implements the safe & collaborative architecture.
Home-page: https://bitbucket.org/fchampalimaud/safe-collaborative-architecture
Author: ['Ricardo Ribeiro']
Author-email: ricardojvr@gmail.com
License: UNKNOWN
Platform: UNKNOWN
Requires-Dist: send2trash
